__init__.py
agent_torch_visualize-0.1.0.dist-info/METADATA
agent_torch_visualize-0.1.0.dist-info/WHEEL
agent_torch_visualize-0.1.0.dist-info/entry_points.txt
geoplot.py
agent_torch_visualize-0.1.0.dist-info/RECORD
