Metadata-Version: 2.1
Name: agent-torch-visualize
Version: 0.1.0
Summary: visualizing large population models
Author: Vedant Kulkarni
License: MIT
Project-URL: Homepage, https://lpm.media.mit.edu/docs
Project-URL: Issues, https://github.com/AgentTorch/visualize/issues
Requires-Python: >=3.8
Requires-Dist: numpy
Requires-Dist: pandas
